{
  "id": "chicken-salad-p0332",
  "book": "Boston Cooking-School Cook Book",
  "year": 1896,
  "title": "Chicken Salad",
  "category": "Meats & Poultry",
  "tags": [
    "1896"
  ],
  "time": {
    "prep": "Variable",
    "cook": "Variable",
    "total": "See instructions"
  },
  "servings": "Variable",
  "ingredients": [],
  "instructions": [
    "one-half Cut cold inch boiled dice. fowl or remnants of roast chicken in",
    "cut pare in cucumbers, halves crosswise. remove thick ‘Take-out slices centres, from each put end, cups and in"
  ],
  "notes": [],
  "source": {
    "page": 332,
    "pdf_url": "https://archive.org/details/bostoncookingsch00farm/page/332"
  },
  "ai": {
    "page_image": "/recipes/boston/pages/0332.png",
    "tokens": [],
    "field_confidence": {
      "title": 0.6145049631595612,
      "ingredients": 0.0,
      "instructions": 0.8831528874798718
    }
  }
}