{
  "id": "cream-dressing-i-p0330",
  "book": "Boston Cooking-School Cook Book",
  "year": 1896,
  "title": "Cream Dressing I.",
  "category": "Desserts & Sweets",
  "tags": [
    "1896"
  ],
  "time": {
    "prep": "Variable",
    "cook": "Variable",
    "total": "See instructions"
  },
  "servings": "Variable",
  "ingredients": [
    "Lobster Salad 11.",
    "Lobster Salad 11.",
    "cold a quantity Moisten salad or dish, of with cele water, pile any slightly s cream then for Lobster drained in or centre, oil Salad dressing. and cover 8, dried I. kept with Add one Arrange in dressing, an a hour towel. equal on in",
    "garnish a curled sieve,",
    "To",
    "ice"
  ],
  "instructions": [
    "pare lobster a",
    "sprinkle with lobster coral forced through a fine",
    "the make length five cuts pieces. parallel Make with each six cuts other, extending one-third",
    "wise Remove by beginning large claws the and split a lobster in two length-"
  ],
  "notes": [],
  "source": {
    "page": 330,
    "pdf_url": "https://archive.org/details/bostoncookingsch00farm/page/330"
  },
  "ai": {
    "page_image": "/recipes/boston/pages/0330.png",
    "tokens": [],
    "field_confidence": {
      "title": 0.5,
      "ingredients": 0.5769137154850695,
      "instructions": 0.7096505593153692
    }
  }
}