{
  "id": "various-fish-used-for-food-p0178",
  "book": "Boston Cooking-School Cook Book",
  "year": 1918,
  "title": "VARIOUS FISH USED FOR FOOD.",
  "category": "Historical",
  "tags": [
    "1918",
    "fanny-farmer",
    "historical"
  ],
  "time": {
    "prep": "Variable",
    "cook": "Variable",
    "total": "See instructions"
  },
  "servings": "Variable",
  "ingredients": [
    ".",
    ";",
    ":",
    ".",
    ".",
    ".",
    ".",
    ".",
    "Shad, roe\\1",
    "}",
    ": y Whitefish... Trout Turbot\\1\\1 535 103 uuot 8 s be n",
    "Crabs, Clams, Oysters, Lobsters soft out solid.\\1 of shell. shell\\1\\1\\1\\1\\1 617 10.6 15.8 5.9 64. 15 1 1 2. 9 33 7 883 80.",
    "W. 0. Atwater, Ph.D."
  ],
  "instructions": [],
  "notes": [],
  "source": {
    "page": 178,
    "pdf_url": "https://archive.org/details/bostoncookingsch00farm/page/178"
  },
  "ai": {
    "page_image": "/recipes/boston/pages/0178.png",
    "tokens": [],
    "field_confidence": {
      "title": 0.5,
      "ingredients": 0.6633855297997757,
      "instructions": 0.0
    }
  }
}